earth_osm/VERSION
earth_osm/__init__.py
earth_osm/__main__.py
earth_osm/args.py
earth_osm/backends.py
earth_osm/eo.py
earth_osm/export.py
earth_osm/extract.py
earth_osm/filter.py
earth_osm/gfk_data.py
earth_osm/gfk_download.py
earth_osm/overpass.py
earth_osm/planet.py
earth_osm/regions.py
earth_osm/stream.py
earth_osm/tagdata.py
earth_osm/taginfo.py
earth_osm/utils.py
earth_osm/__pycache__/__init__.cpython-314.pyc
earth_osm/data/earth_data.json
earth_osm/data/gfk_index.csv
earth_osm/osmpbf/README.md
earth_osm/osmpbf/__init__.py
earth_osm/osmpbf/file.py
earth_osm/osmpbf/fileformat_pb2.py
earth_osm/osmpbf/osmformat_pb2.py
earth_osm-3.0.2.dist-info/licenses/LICENSE
earth_osm-3.0.2.dist-info/METADATA
earth_osm-3.0.2.dist-info/WHEEL
earth_osm-3.0.2.dist-info/entry_points.txt
earth_osm-3.0.2.dist-info/top_level.txt
earth_osm-3.0.2.dist-info/RECORD
