Metadata-Version: 2.4
Name: earth_osm
Version: 3.0.2
Summary: Python tool to extract large-amounts of OpenStreetMap data
Author: pypsa-meets-earth
License: MIT License
Project-URL: Homepage, https://github.com/pypsa-meets-earth/earth-osm/
Project-URL: Issues, https://github.com/pypsa-meets-earth/earth-osm/issues
Classifier: Programming Language :: Python :: 3.8
Classifier: Programming Language :: Python :: 3.9
Classifier: Programming Language :: Python :: 3.10
Classifier: Programming Language :: Python :: 3.11
Classifier: Programming Language :: Python :: 3.12
Classifier: Development Status :: 5 - Production/Stable
Classifier: Environment :: Console
Classifier: Intended Audience :: Science/Research
Classifier: License :: OSI Approved :: MIT License
Classifier: Natural Language :: English
Classifier: Operating System :: OS Independent
Requires-Python: >=3.8
License-File: LICENSE
Requires-Dist: geopandas
Requires-Dist: pandas
Requires-Dist: tqdm
Requires-Dist: requests
Requires-Dist: protobuf>=4.21.1
Provides-Extra: dev
Requires-Dist: pytest; extra == "dev"
Requires-Dist: coverage; extra == "dev"
Requires-Dist: flake8; extra == "dev"
Requires-Dist: black; extra == "dev"
Requires-Dist: isort; extra == "dev"
Requires-Dist: pytest-cov; extra == "dev"
Requires-Dist: codecov; extra == "dev"
Requires-Dist: mypy>=0.9; extra == "dev"
Requires-Dist: gitchangelog; extra == "dev"
Requires-Dist: mkdocs; extra == "dev"
Requires-Dist: osmium; extra == "dev"
Provides-Extra: docs
Requires-Dist: lazydocs; extra == "docs"
Requires-Dist: mkdocs; extra == "docs"
Requires-Dist: mkdocs-material; extra == "docs"
Requires-Dist: mkdocs-awesome-pages-plugin; extra == "docs"
Requires-Dist: mkdocstrings[python]; extra == "docs"
Requires-Dist: markdown-include; extra == "docs"
Dynamic: license-file
